cl_assistant-1.0.1.dist-info/licenses/LICENSE
cla/__init__.py
cla/__main__.py
cla/chat.py
cl_assistant-1.0.1.dist-info/METADATA
cl_assistant-1.0.1.dist-info/WHEEL
cl_assistant-1.0.1.dist-info/entry_points.txt
cl_assistant-1.0.1.dist-info/top_level.txt
cl_assistant-1.0.1.dist-info/RECORD
