Metadata-Version: 2.4
Name: cl-assistant
Version: 1.0.1
Summary: Command Line AI Assistant
Author: Paulo Lira
License: MIT
Requires-Python: >=3.9
License-File: LICENSE
Requires-Dist: httpx
Dynamic: license-file
